<?xml version="1.0" encoding="utf-8" ?>
<PerformanceCounter InstanceName="SiteController">
  <!-- Category
       Name:Performance counter category name  
       Description:Peformance counter category description  -->
  <!-- Counter 
       ID:Unique identifier for each counter
       Name:Counter name
       Type:Performance Counter Type for each counter
       Description:Performance counter description -->
  <!-- Type: NumberOfItemsHEX32 = 0,
               NumberOfItemsHEX64 = 256,
               NumberOfItems32 = 65536,
               NumberOfItems64 = 65792,
               CounterDelta32 = 4195328,
               CounterDelta64 = 4195584,
               SampleCounter = 4260864,
               CountPerTimeInterval32 = 4523008,
               CountPerTimeInterval64 = 4523264,
               RateOfCountsPerSecond32 = 272696320,
               RateOfCountsPerSecond64 = 272696576,
               RawFraction = 537003008,
                CounterTimer = 541132032,
                Timer100Ns = 542180608,
                SampleFraction = 549585920,
                CounterTimerInverse = 557909248,
                Timer100NsInverse = 558957824,
                CounterMultiTimer = 574686464,
                CounterMultiTimer100Ns = 575735040,
                CounterMultiTimerInverse = 591463680,
                CounterMultiTimer100NsInverse = 592512256,
                AverageTimer32 = 805438464,
                ElapsedTime = 807666944,
                AverageCount64 = 1073874176,
                SampleBase = 1073939457,
                AverageBase = 1073939458,
                RawBase = 1073939459,
                CounterMultiBase = 1107494144,   
    -->  
  <Category Name="Application" Description="Monitor current application preformance">
    <Counter ID="1" Name="Total Threads" Type="NumberOfItems32" Description="Shows number of active threads" />
  </Category>
  <Category Name="Transaction" Description="Application Transaction status">
    <Counter ID="2" Name="Transaction Committed" Type="NumberOfItems32" Description="Shows number of transaction commited"/>
    <Counter ID="3" Name="Transaction Rollback" Type="NumberOfItems32" Description="Shows number of transaction rolled back" />
  </Category>
  <Category Name="Method2" Description="Monitor current method preformance">
    <Counter ID="4" Name="Total Method1 Threads" Type="NumberOfItems32" Description="Shows number of active threads in method" />
    <Counter ID="5" Name="Total Method2 Threads" Type="NumberOfItems32" Description="Shows number of active threads in method"/>
  </Category>
</PerformanceCounter>